recc_storage/__init__.py
recc_storage/storage.py
recc_storage-2.1.0.dist-info/LICENSE
recc_storage-2.1.0.dist-info/METADATA
recc_storage-2.1.0.dist-info/WHEEL
recc_storage-2.1.0.dist-info/top_level.txt
recc_storage-2.1.0.dist-info/RECORD
